tracktable/__init__.py
tracktable/README.md
tracktable/LICENSE.txt
tracktable/core/misc.py
tracktable/core/log.py
tracktable/core/conversions.py
tracktable/core/testutils.py
tracktable/core/test_utilities.py
tracktable/core/__init__.py
tracktable/core/core_types.py
tracktable/core/simple_timezone.py
tracktable/core/timestamp.py
tracktable/core/geomath.py
tracktable/analysis/__init__.py
tracktable/algorithms/boxiness.py
tracktable/algorithms/__init__.py
tracktable/algorithms/dbscan.py
tracktable/algorithms/distance_geometry.py
tracktable/render/render_heatmap.py
tracktable/render/mapmaker.py
tracktable/render/__init__.py
tracktable/render/render_movie.py
tracktable/render/render_trajectories.py
tracktable/render/render_map.py
tracktable/render/backends/patch_cartopy_download_url.py
tracktable/render/backends/ipyleaflet_backend.py
tracktable/render/backends/folium_backend.py
tracktable/render/backends/__init__.py
tracktable/render/backends/ffmpeg_backend.py
tracktable/render/backends/bokeh_backend.py
tracktable/render/backends/cartopy_backend.py
tracktable/render/backends/folium_proxy.py
tracktable/render/map_processing/common_processing.py
tracktable/render/map_processing/maps.py
tracktable/render/map_processing/paths.py
tracktable/render/map_processing/__init__.py
tracktable/render/map_processing/movies.py
tracktable/render/map_processing/parallel_movies.py
tracktable/render/map_decoration/coloring.py
tracktable/render/map_decoration/clock.py
tracktable/render/map_decoration/__init__.py
tracktable/render/map_decoration/colormaps.py
tracktable/render/map_decoration/geographic_decoration.py
tracktable/.dylibs/libTracktableCore.1.7.3.dylib
tracktable/.dylibs/libboost_thread.dylib
tracktable/.dylibs/libboost_python311.dylib
tracktable/.dylibs/libTracktableDomain.1.7.3.dylib
tracktable/.dylibs/libboost_graph.dylib
tracktable/.dylibs/libboost_container.dylib
tracktable/.dylibs/libc++.1.0.dylib
tracktable-1.7.3.dist-info/RECORD
tracktable-1.7.3.dist-info/WHEEL
tracktable-1.7.3.dist-info/top_level.txt
tracktable-1.7.3.dist-info/METADATA
tracktable-1.7.3.dist-info/licenses/Python/tracktable/LICENSE.txt
