Metadata-Version: 2.4
Name: tracktable
Version: 1.7.3
Author: Andy Wilson, Danny Rintoul, Chris Valicka, Ben Newton, Paul Schrum, Phil Baxley, Kat Ward, Rick Vinyard, Michael Scoggin, Michael Fadem, Geoff Danielson, Erik Strobert
Maintainer: "Andy Wilson"
Maintainer-email: Andy Wilson <atwilso@sandia.gov>, Phil Baxley <pabaxle@sandia.gov>
License-Expression: BSD-3-Clause
Project-URL: homepage, https://tracktable.sandia.gov
Project-URL: documentation, https://tracktable.readthedocs.io
Project-URL: repository, https://github.com/sandialabs/tracktable
Project-URL: changelog, https://github.com/sandialabs/tracktable/blob/main/CHANGELOG.md
Keywords: trajectory,analysis,visualization
Classifier: Development Status :: 5 - Production/Stable
Classifier: Intended Audience :: Developers
Classifier: Natural Language :: English
Classifier: Operating System :: POSIX :: Linux
Classifier: Operating System :: MacOS :: MacOS X
Classifier: Operating System :: Microsoft :: Windows
Classifier: Programming Language :: Python :: 3
Classifier: Programming Language :: Python :: 3.9
Classifier: Programming Language :: Python :: 3.10
Classifier: Programming Language :: Python :: 3.11
Classifier: Programming Language :: Python :: 3.12
Classifier: Programming Language :: Python :: 3.13
Classifier: Programming Language :: C++
Classifier: Programming Language :: Python :: Implementation :: CPython
Classifier: Topic :: Scientific/Engineering :: Information Analysis
Classifier: Topic :: Scientific/Engineering :: Visualization
Classifier: Topic :: Scientific/Engineering :: GIS
Requires-Python: >=3.9
License-File: Python/tracktable/LICENSE.txt
Requires-Dist: cartopy
Requires-Dist: folium
Requires-Dist: matplotlib
Requires-Dist: numpy
Requires-Dist: pyshp
Requires-Dist: pytz
Requires-Dist: six
Requires-Dist: shapely
Requires-Dist: tqdm
Requires-Dist: tracktable-data
Dynamic: license-file
